{
  "extraction_id": "04b120c8",
  "filename": "4292312_E14_SEN_X_01_001_002_XX_04_005_X_XXX.pdf",
  "success": true,
  "processing_time_ms": 31284,
  "corporacion": "SENADO",
  "departamento": "ANTIOQUIA V",
  "municipio": "MEDELLIN",
  "zona": "02",
  "puesto": "|.E.FEDERICO CARRASQUILLA |",
  "mesa": "005",
  "partidos": [
    {
      "party_name": "SENADO",
      "party_code": "",
      "votes": 0,
      "confidence": 0.5,
      "needs_review": true
    },
    {
      "party_name": "COALICIÓN ALIANZA VERDE Y CENTRO ESPERANZA",
      "party_code": "",
      "votes": 255,
      "confidence": 0.75,
      "needs_review": false
    },
    {
      "party_name": "S1 ¿ 0003 ' PARTIDO CAMBIO",
      "party_code": "",
      "votes": 3,
      "confidence": 0.5,
      "needs_review": true
    },
    {
      "party_name": "KEESZ. 0019 PARTIDO NUEVO LIBERALISMO",
      "party_code": "",
      "votes": 19,
      "confidence": 0.75,
      "needs_review": false
    },
    {
      "party_name": "COALICIÓN MIRA",
      "party_code": "",
      "votes": 231,
      "confidence": 0.75,
      "needs_review": false
    },
    {
      "party_name": "MOVIMIENTO GENTE NUEVA",
      "party_code": "",
      "votes": 1186,
      "confidence": 0.5,
      "needs_review": true
    },
    {
      "party_name": "0292 PACTO HISTÓRICO >",
      "party_code": "",
      "votes": 292,
      "confidence": 0.75,
      "needs_review": false
    },
    {
      "party_name": "ds 0177 PARTIDO INDÍGENA COLOMBIANO P.,C",
      "party_code": "",
      "votes": 177,
      "confidence": 0.5,
      "needs_review": true
    },
    {
      "party_name": "AUSAS",
      "party_code": "",
      "votes": 0,
      "confidence": 0.5,
      "needs_review": true
    }
  ],
  "total_votos": 2163,
  "votos_blancos": 0,
  "votos_nulos": 0,
  "confidence": 1.0,
  "raw_text": "- e\n710597202010111 Ver 01 Pag: 01 de 11 0\nACTA DE ESCRUTINIO DE LOS 1573 |\n[m]; E [m] JURADOS DE VOTACIÓN ¡\nA ia L\nea DELEGADOS e |\nel E Uyk y ELECCIÓNES CÓNGRESO PS |\nE 13 DE MARZO DE 2022 Eo, V\nSO pEOISTiADEA\nOrar SENADO 0\nDEPARTAMENTO: 01 - ANTIOQUIA V\nMUNICIPIO: 001 - MEDELLIN 0\nLUGAR: |.E.FEDERICO CARRASQUILLA |\nZONA: 02 PUESTO: 04 MESA: 005\nX 4-29-23-12 X :\nTOTAL TOTAL TOTAL í\nSUFRAGANTES VOTOS VOTOS Í\nFORMATO E-11 EN LA URNA  INCINERADOS\nCIRCUNSCRIPCIÓN NACIONAL (\n\n0 ] S | 0013 | PARTIDO COMUNES | |\n| 0 | VOTOS POR LA AGRUPACIÓN POLÍTICA —> |-|—|[—| 0\n|\n\n|\n\nMN No. Form: $9720 KIT 59,720 Civ1216887 Ml ¡\n\n--- PAGE BREAK ---\n:\n- e\n710597202010211 Ver: 01 Pag: 02 de 11 |\nACTA DE ESCRUTINIO DE LOS 7 0\n[u] A [m] JURADOS DE VOTACION |\ne ira DELEGADOS -\nSr a ELECCIONES CONGRESO E |\ndal ELO 13 DE MARZO DE 2022 E !\ne O RESIPICADDRÍA\nOr anto SENADO |\nDEPARTAMENTO: 01 - ANTIOQUIA |\nMUNICIPIO: 001 - MEDELLIN |\nLUGAR: |.E.FEDERICO CARRASQUILLA |\nZONA: 02 PUESTO: 04 MESA: 005 |\nXA 4-29-23-12 X |\nLU 777 STA CON VOTO PREFERENTE 100077 ¡\n| ¡ | 0255 ¡ COALICIÓN ALIANZA VERDE Y CENTRO ESPERANZA ¡\n| O | | | VOTOS SOLO POR LA AGRUPACIÓN POLÍTICA ¡\n2 | MS: 35 pop | 69 | |\n| O o | E |\na... - - t.- o A. -=o --h- o a ES po —— po PA —pua —\nAA Pa\nNN (\nY rm —Á A ——— E + ——\n3 Sil moco oo loma jo ¡\nE ! j 42; | i [ 76 | | |\na e a ee ii it E E ¡\nMO | | li 43: | ! A 77 | | SS\n¡ | | | | | | 1 (\npa too poo] 53 io io oa i—¡— | |\n] | ! a a 1\nAo O PL |\na | IN | o |\nO A E ]\nA po: A A ap + a | : ;\n18 = za SN | as 1 | €\nE il 52 | 86 i | |\ne\no 22 poo! [ 55 o do; 89 :\nBoss A ¿ss | |\n26 Il Tp 93 |\nA oi] O EL o |\nE O | 95 O\n290 | | LO B2 lo doi 96 po V\n. J : : ! : |\nBd | 64 1 io y 98 po ¡\nO : : : | )\nTOTAL = VOTOS AGRUPACIÓN + VOTOS CANDIDATOS I—[ 411] 0\n|\n|\n|\n|\n!\n:\n|\nMl No. Form: 59720 KIT 59,720 Clvi216688 Ml '\nJ\n!\n\n--- PAGE BREAK ---\nÍ\nA o\n710597202010311 Ver: 01 Pag: 03 de 11\nACTA DE ESCRUTINIO DE LOS 7 ¡\n[m] e. [m] JURADOS DE VOTACION |\nTE DELEGADOS o |\nES ELECCIONES CONGRESO a: |\ndea 13 DE MARZO DE 2022 ¡a |\nORT REGISTRADURÍA\n|\nDEPARTAMENTO: 01 - ANTIOQUIA\nMUNICIPIO: 001 - MEDELLIN |\nLUGAR: 1.E.FEDERICO CARRASQUILLA -:\nZONA: 02 PUESTO: 04 MESA: 005 :\nX 4-29-23-12 X |\nLo y o LISTA CÓN VOTO PREFERENTE 7 |\n| ==\": ] !\nj ¡ | 1140 | FUERZA CIUDADANA LA FUERZA DEL CAMBIO |\n0 Ll EN | «=== VOTOS SOLO POR LA AGRUPACIÓN POLÍTICA\n2 O: | 33 O E E | V\nA ai A PA: A t\nO CN 66 ot ¡\na | =| sti 67 A i\nSA A TOA\nA pe O A [E Fo |\nmn — — A A AA A A pk A a Á A So 1\nO A A: | y\n.- —- a A AAXÁAAÁ AA AA AA A —Á —— -\nIT: ADE | + | | |\nO pq iy o 78 | o ¡\nO: 45 | = ra |: E |\nA] Bos L 80 Loy |\ne a a A A a : ¡ !\nMa a ICA A EJ\nO Y 50 | ES ! 0\nE. | O Y: NN ¡\nIC ol 52 0 j O 85 | | '\nO A od ¡\nE des |] ¡\n: | : Bb: ( |\nA E A E | AS E A do Lio |\nO O CA O ZO |\n25 | | P 58, | ¡ o at | | l |\n| ero | 588.0 00 4 Mosa 1 Pol] 'Ñ\nA O 9 j 1] ]\nST] | | 62; ¡ j E\nTOTAL = VOTOS AGRUPACIÓN + VOTOS CANDIDATOS E\n|\n|\nE\npi\nM No, Form: 59720 KIT 59,720 Civ1216859 Ml j E\n\n--- PAGE BREAK ---\n¡\nm n\n| ¡\n| 710597202010411 Ver: 01 Pag: 04 de 11\nACTA DE ESCRUTINIO DE LOS Eta\nol a [=] JURADOS DE VOTACIÓN\n\"ll\" |\n: sE PTE DELEGADOS\nMora iH]! ELECCIONES CONGRESO 9\nPE Ec 13 DE MARZO DE 2022 EE:\n[rhy an REGISTRADDRÍA\n[m] 5%.\" ES SENADO\nDEPARTAMENTO: 01 - ANTIOQUIA\nMUNICIPIO: 001 - MEDELLIN\nLUGAR: |.E.FEDERICO CARRASQUILLA\nZONA: 02 PUESTO: 04 MESA: 005\nX 4-29-23-12 Á\no LISTACON VOTO PREFERENTE\n: : S1 ¿ 0003 ' PARTIDO CAMBIO RADICAL.\n0 | | ] | «Eo. VOTOS SOLO POR LA AGRUPACIÓN POLÍTICA\npo 2 ¡ ¡ 36; | Ñ 70 |\n3 O 7 Po\nLB Me o\nBE IP\nA Go DI -——\nO 75 |]\n| po 44: | 78\ndm MAN»1==2=%4+4h o —— a .\nIN 0 45 to] | 79 E |\ni a  — — A A A\nE\nST ACIDO EC E\n15 4 io] 49 to io | : 83 |\n| L |\nCI A E O o\nA A A O:\n| 18 : | | Í 52 | E 86 | ! |\ne —— 2 |\nE : 3 583 00000 1 87 |\nIC IC\n07 + E $ygAA=- AA XA TA '\nBo . 55 ao; . 89 | E:\n22; | 56: : i 90 | | |\n| 23 | A Br io io E 91 Po:\nTE ! 58 ' H 931 | ¡ |\n2 |. 26! 0 E 0 94 3 | !\n28 | ! 7 6 ocio; ¡Ms Lo;\n| A AAA A CI | ÓN\n29 | | 6e2 o 3 ii sr lo dol]\nBO | Lo o 63: o 0: 98 | |\nIN: a A 99 |\nES os 400 |\nO IIA | a _\ngr ¡Mc E\n) AS OA TA | E O\nTOTAL = VOTOS AGRUPACIÓN + VOTOS CANDIDATOS\n| | 9505 | 4073 | SALUD SOS COLOMBIA. SECTOR ORGANIZADO DE LA,\nE ... - A PA -\n¡ 0 VOTOS POR LA AGRUPACIÓN POLÍTICA \"> [JJ 1]\no A . 2 _USTA SIN VOTO PREFERENTE A |\n| | KEesz. ¡ 0019 | PARTIDO NUEVO LIBERALISMO |\n| ' VOTOS POR LA AGRUPACIÓN POLÍTICA mul\n|\nA KIT 59,720 civizissoo MM\n\n--- PAGE BREAK ---\no NM .\n710597202010511 Ver: 01 Pag: D5 de 11:\nACTA DE ESCRUTINIO DE LOS EA\n[m]pos 35h] JURADOS DE VOTACIÓN |\nA a\nii DELEGADOS - |\npate q ELECCIONES CONGRESO FED |\nELN 13 DE MARZO DE 2022 E\nEE pecismanera\nA PA SENADO '\nÍ\nDEPARTAMENTO: 01 - ANTIOQUIA :\nj\nMUNICIPIO: 001 - MEDELLIN 1\nLUGAR: I.E.FEDERICO CARRASQUILLA ]\nZONA: 02 PUESTO: 04 MESA: 005 |\nÍ\n1\nX 4-29-23-12 X ]\nIT TUnSTA SIN VOTO PREFERENTE TUTO IT\n| | ro : 1130 ; ESTAMOS LISTAS COLOMBIA '\n| O 3 VOTOSPORLA AGRUPACIÓN POLÍTICA mul» |\nOT TISTASIN VOTO PREFERENTE ]\n0 | dE ¡4039 | MOVIMIENTO UNITARIO METAPOLITICO l\nDo VOTOS POR LA AGRUPACIÓN POLÍTICA mu» EI | |\n| | el",
  "warnings": [
    "Total calculated from party votes"
  ],
  "error": null
}